[{"repository":{"name":"hugo-academic","url":"https://github.com/gcushen/hugo-academic","updatedAt":"2020-08-01T20:44:30Z","forks":{"totalCount":2113},"stargazers":{"totalCount":4810}},"tags":["widgets","resume","portfolio","responsive","clean","personal","company","blog","minimal","light","dark","multilingual","documentation","landing page","projects","single page","contact form","mobile","gallery","search","presentation","simple","minimalist","starter","modern","one page","customizable","technical","product","slide"]},{"repository":{"name":"hugo-theme-even","url":"https://github.com/olOwOlo/hugo-theme-even","updatedAt":"2020-08-01T07:25:03Z","forks":{"totalCount":460},"stargazers":{"totalCount":1159}},"tags":["responsive","blog","simple","clean","highlight.js","syntax highlighting"]},{"repository":{"name":"hugo-coder","url":"https://github.com/luizdepra/hugo-coder","updatedAt":"2020-07-30T02:42:42Z","forks":{"totalCount":487},"stargazers":{"totalCount":1064}},"tags":["blog","minimal","minimalist","responsive","simple","clean","personal"]},{"repository":{"name":"hugo-theme-learn","url":"https://github.com/matcornic/hugo-theme-learn","updatedAt":"2020-08-01T01:23:42Z","forks":{"totalCount":626},"stargazers":{"totalCount":992}},"tags":["documentation","grav","learn","doc","search"]},{"repository":{"name":"docsy","url":"https://github.com/google/docsy","updatedAt":"2020-08-01T15:15:16Z","forks":{"totalCount":200},"stargazers":{"totalCount":865}},"tags":["documentation","multilingual","customizable","responsive","docs"]},{"repository":{"name":"hugo-book","url":"https://github.com/alex-shpak/hugo-book","updatedAt":"2020-08-01T13:37:32Z","forks":{"totalCount":363},"stargazers":{"totalCount":782}},"tags":["responsive","clean","documentation","docs","flexbox","search","mobile","multilingual","disqus"]},{"repository":{"name":"beautifulhugo","url":"https://github.com/halogenica/beautifulhugo","updatedAt":"2020-07-30T22:28:13Z","forks":{"totalCount":376},"stargazers":{"totalCount":733}},"tags":["blog","company","portfolio","projects","minimal","responsive","seo","google analytics","bootstrap","disqus","light","syntax highlighting","multilingual","portfolio","projects","mobile","technical"]},{"repository":{"name":"hermit","url":"https://github.com/Track3/hermit","updatedAt":"2020-07-29T03:05:02Z","forks":{"totalCount":228},"stargazers":{"totalCount":652}},"tags":["blog","minimal","dark","responsive"]},{"repository":{"name":"hugo-tranquilpeak-theme","url":"https://github.com/kakawait/hugo-tranquilpeak-theme","updatedAt":"2020-07-31T06:48:19Z","forks":{"totalCount":367},"stargazers":{"totalCount":637}},"tags":["blog","minimal","responsive","personal","customizable","creative","fontawesome","highlight.js"]},{"repository":{"name":"hugo-theme-hello-friend-ng","url":"https://github.com/rhazdon/hugo-theme-hello-friend-ng","updatedAt":"2020-08-01T22:57:15Z","forks":{"totalCount":341},"stargazers":{"totalCount":606}},"tags":["blog","clean","customizable","dark","highlighting","light","minimal","monochromatic","multilingual","personal","responsive","simple","technical"]},{"repository":{"name":"LoveIt","url":"https://github.com/dillonzq/LoveIt","updatedAt":"2020-08-01T16:31:36Z","forks":{"totalCount":251},"stargazers":{"totalCount":580}},"tags":["blog","clean","responsive","dark","theme"]},{"repository":{"name":"hugo-theme-jane","url":"https://github.com/xianmin/hugo-theme-jane","updatedAt":"2020-07-31T01:29:17Z","forks":{"totalCount":217},"stargazers":{"totalCount":574}},"tags":["responsive","blog","simple","clean","readable","highlight","multilingual"]},{"repository":{"name":"hugo-theme-terminal","url":"https://github.com/panr/hugo-theme-terminal","updatedAt":"2020-07-31T22:12:31Z","forks":{"totalCount":223},"stargazers":{"totalCount":559}},"tags":["blog","clean","customizable","dark","highlighting","minimal","monotone","multilingual","personal","responsive","simple","technical","retro"]},{"repository":{"name":"gohugo-theme-ananke","url":"https://github.com/theNewDynamic/gohugo-theme-ananke","updatedAt":"2020-08-01T00:04:32Z","forks":{"totalCount":485},"stargazers":{"totalCount":481}},"tags":["website","starter","responsive","disqus","blog","tachyons","multilingual","stackbit"]},{"repository":{"name":"hugo-universal-theme","url":"https://github.com/devcows/hugo-universal-theme","updatedAt":"2020-07-29T16:09:10Z","forks":{"totalCount":328},"stargazers":{"totalCount":445}},"tags":["blog","company","portfolio","projects","minimal","responsive"]},{"repository":{"name":"hugo-theme-hello-friend","url":"https://github.com/panr/hugo-theme-hello-friend","updatedAt":"2020-08-01T23:26:38Z","forks":{"totalCount":187},"stargazers":{"totalCount":428}},"tags":["blog","clean","customizable","dark","highlighting","light","minimal","monochromatic","multilingual","personal","responsive","simple","technical"]},{"repository":{"name":"docuapi","url":"https://github.com/bep/docuapi","updatedAt":"2020-07-30T06:24:03Z","forks":{"totalCount":146},"stargazers":{"totalCount":428}},"tags":["documentation","api","docs","responsive","multilingual"]},{"repository":{"name":"minimo","url":"https://github.com/MunifTanjim/minimo","updatedAt":"2020-08-01T16:29:31Z","forks":{"totalCount":176},"stargazers":{"totalCount":420}},"tags":["blog","minimal","minimalist","responsive","google-analytics"]},{"repository":{"name":"hugo-paper","url":"https://github.com/nanxiaobei/hugo-paper","updatedAt":"2020-07-28T20:45:03Z","forks":{"totalCount":90},"stargazers":{"totalCount":418}},"tags":["responsive","simple","clean","light","white","blog"]},{"repository":{"name":"Mainroad","url":"https://github.com/Vimux/Mainroad","updatedAt":"2020-07-30T09:37:19Z","forks":{"totalCount":246},"stargazers":{"totalCount":412}},"tags":["blog","responsive","customizable","widgets","rss","disqus","google analytics","wordpress"]},{"repository":{"name":"hyde","url":"https://github.com/spf13/hyde","updatedAt":"2020-07-27T16:08:26Z","forks":{"totalCount":249},"stargazers":{"totalCount":405}},"tags":["blog","company"]},{"repository":{"name":"hugo-theme-introduction","url":"https://github.com/victoriadrake/hugo-theme-introduction","updatedAt":"2020-08-01T22:59:06Z","forks":{"totalCount":145},"stargazers":{"totalCount":351}},"tags":["blog","bulma","clean","dark","disqus","font awesome","gallery","minimal","minimalist","mobile","multilingual","one page","personal","responsive","simple","single page","starter","syntax highlighting","projects","white"]},{"repository":{"name":"kube","url":"https://github.com/jeblister/kube","updatedAt":"2020-08-01T19:56:17Z","forks":{"totalCount":98},"stargazers":{"totalCount":337}},"tags":["responsive","kube","documentation","landing","blog","themes","professional","modern"]},{"repository":{"name":"hugo-theme-cactus-plus","url":"https://github.com/nodejh/hugo-theme-cactus-plus","updatedAt":"2020-07-29T12:42:40Z","forks":{"totalCount":140},"stargazers":{"totalCount":334}},"tags":["blog","beautiful","disqus","rss","syntax highlighting","tags"]},{"repository":{"name":"LeaveIt","url":"https://github.com/liuzc/LeaveIt","updatedAt":"2020-07-23T10:30:04Z","forks":{"totalCount":107},"stargazers":{"totalCount":313}},"tags":["blog","minimal","clean","responsive","gallery","dark","theme"]},{"repository":{"name":"minimal","url":"https://github.com/calintat/minimal","updatedAt":"2020-07-28T19:22:24Z","forks":{"totalCount":180},"stargazers":{"totalCount":302}},"tags":["blog","minimal","personal","responsive"]},{"repository":{"name":"hugo-xmin","url":"https://github.com/yihui/hugo-xmin","updatedAt":"2020-08-01T12:32:00Z","forks":{"totalCount":149},"stargazers":{"totalCount":300}},"tags":["minimal","blog","personal","clean","simple","starter","minimalist"]},{"repository":{"name":"reveal-hugo","url":"https://github.com/dzello/reveal-hugo","updatedAt":"2020-07-29T17:10:19Z","forks":{"totalCount":74},"stargazers":{"totalCount":298}},"tags":["presentation","revealjs"]},{"repository":{"name":"hugo-future-imperfect","url":"https://github.com/jpescador/hugo-future-imperfect","updatedAt":"2020-07-29T23:59:05Z","forks":{"totalCount":208},"stargazers":{"totalCount":297}},"tags":["blog","responsive","font awesome","highlight.js","fancybox 3","staticman","netlify"]},{"repository":{"name":"hugo-theme-meme","url":"https://github.com/reuixiy/hugo-theme-meme","updatedAt":"2020-07-30T02:43:02Z","forks":{"totalCount":89},"stargazers":{"totalCount":296}},"tags":["blog","minimal","clean","typography","multilingual"]},{"repository":{"name":"hugo-theme-sam","url":"https://github.com/victoriadrake/hugo-theme-sam","updatedAt":"2020-08-02T00:08:00Z","forks":{"totalCount":135},"stargazers":{"totalCount":278}},"tags":["clean","simple","blog","portfolio","flexbox","css grid","minimalist","responsive","syntax highlighting","gallery","starter"]},{"repository":{"name":"hugo-theme-zzo","url":"https://github.com/zzossig/hugo-theme-zzo","updatedAt":"2020-08-01T12:52:33Z","forks":{"totalCount":115},"stargazers":{"totalCount":269}},"tags":["accessible","multilingual","responsive","blog","search","simple","light","dark","mobile","gallery","technical","fast","presentation"]},{"repository":{"name":"hugo-creative-portfolio-theme","url":"https://github.com/kishaningithub/hugo-creative-portfolio-theme","updatedAt":"2020-07-28T07:14:24Z","forks":{"totalCount":167},"stargazers":{"totalCount":265}},"tags":["creative","portfolio","projects","minimal","responsive"]},{"repository":{"name":"blackburn","url":"https://github.com/yoshiharuyamashita/blackburn","updatedAt":"2020-07-25T12:41:50Z","forks":{"totalCount":156},"stargazers":{"totalCount":259}},"tags":["blog","personal","purecss","responsive"]},{"repository":{"name":"kiss","url":"https://github.com/ribice/kiss","updatedAt":"2020-07-25T20:34:50Z","forks":{"totalCount":107},"stargazers":{"totalCount":237}},"tags":["blog","minimal","minimalist","responsive"]},{"repository":{"name":"hugo-theme-cleanwhite","url":"https://github.com/zhaohuabing/hugo-theme-cleanwhite","updatedAt":"2020-07-31T14:48:17Z","forks":{"totalCount":118},"stargazers":{"totalCount":228}},"tags":["minimal","responsive","blog","light","clean","search"]},{"repository":{"name":"ezhil","url":"https://github.com/vividvilla/ezhil","updatedAt":"2020-08-01T19:38:43Z","forks":{"totalCount":127},"stargazers":{"totalCount":201}},"tags":["minimal","clean","blog","responsive","personal","simple","minimalist","portfolio","dark"]},{"repository":{"name":"hugo-theme-zozo","url":"https://github.com/varkai/hugo-theme-zozo","updatedAt":"2020-07-31T01:56:44Z","forks":{"totalCount":60},"stargazers":{"totalCount":198}},"tags":["blog","beautiful","simple","valine","rss","syntax highlighting","tags"]},{"repository":{"name":"hyde-hyde","url":"https://github.com/htr3n/hyde-hyde","updatedAt":"2020-07-29T11:53:03Z","forks":{"totalCount":179},"stargazers":{"totalCount":193}},"tags":["blog","theme","hyde","highlight.js","font-awesome","google analytics","disqus","personal","syntax highlighting","responsive","graphcomment"]},{"repository":{"name":"hugo-notepadium","url":"https://github.com/cntrump/hugo-notepadium","updatedAt":"2020-08-01T09:11:36Z","forks":{"totalCount":85},"stargazers":{"totalCount":187}},"tags":["blog"]},{"repository":{"name":"hugo-orbit-theme","url":"https://github.com/aerohub/hugo-orbit-theme","updatedAt":"2020-07-23T21:49:25Z","forks":{"totalCount":84},"stargazers":{"totalCount":187}},"tags":["cv","resume","colour schemes"]},{"repository":{"name":"bilberry-hugo-theme","url":"https://github.com/Lednerb/bilberry-hugo-theme","updatedAt":"2020-07-31T17:59:44Z","forks":{"totalCount":93},"stargazers":{"totalCount":185}},"tags":["blog","personal","responsive","algolia","disqus","search","font awesome","pages","posts","multilingual","highlight.js","syntax highlighting","premium","shortcuts"]},{"repository":{"name":"hugo-theme-yinyang","url":"https://github.com/joway/hugo-theme-yinyang","updatedAt":"2020-07-29T03:28:09Z","forks":{"totalCount":66},"stargazers":{"totalCount":183}},"tags":["blog","minimal","minimalist","responsive","simple","clean","personal"]},{"repository":{"name":"hugo-goa","url":"https://github.com/shenoybr/hugo-goa","updatedAt":"2020-07-30T06:15:53Z","forks":{"totalCount":103},"stargazers":{"totalCount":181}},"tags":["roboto","lato","roboto slab","bootstrap","font awesome","minimal","clean"]},{"repository":{"name":"hugo-theme-bootstrap4-blog","url":"https://github.com/alanorth/hugo-theme-bootstrap4-blog","updatedAt":"2020-07-31T05:14:02Z","forks":{"totalCount":126},"stargazers":{"totalCount":173}},"tags":["bootstrap","blog","font awesome"]},{"repository":{"name":"meghna-hugo","url":"https://github.com/themefisher/meghna-hugo","updatedAt":"2020-08-01T10:27:59Z","forks":{"totalCount":582},"stargazers":{"totalCount":168}},"tags":["landing-page","google-analytics","fast","modern","minimal","minimalistic","business","agency-template","themefisher","hugo-theme","hugo-templates","bootstrap","blog","responsive","portfolio","single-page","dark","clean","simple","company","creative","contact-form","custom-themes","mobile"]},{"repository":{"name":"tale-hugo","url":"https://github.com/EmielH/tale-hugo","updatedAt":"2020-07-24T08:32:15Z","forks":{"totalCount":79},"stargazers":{"totalCount":166}},"tags":["minimal","clean","responsive","simple","personal","blog","starter","light","typography"]},{"repository":{"name":"hugo-theme-m10c","url":"https://github.com/vaga/hugo-theme-m10c","updatedAt":"2020-07-30T19:50:54Z","forks":{"totalCount":111},"stargazers":{"totalCount":164}},"tags":["blog","minimalistic","minimal","responsive","dark"]},{"repository":{"name":"syna","url":"https://github.com/okkur/syna","updatedAt":"2020-07-30T15:31:01Z","forks":{"totalCount":73},"stargazers":{"totalCount":156}},"tags":["customizable","blog","responsive","clean","personal","bootstrap","portfolio","company","projects","mobile","search","documentation"]},{"repository":{"name":"hugo-elate-theme","url":"https://github.com/saey55/hugo-elate-theme","updatedAt":"2020-07-26T10:26:12Z","forks":{"totalCount":87},"stargazers":{"totalCount":156}},"tags":["elate","hugo","parallax"]},{"repository":{"name":"hugo_theme_pickles","url":"https://github.com/mismith0227/hugo_theme_pickles","updatedAt":"2020-08-01T17:59:24Z","forks":{"totalCount":94},"stargazers":{"totalCount":155}},"tags":["responsive","blog","google analytics","disqus","clean","tags","minimal","minimalist","simple","white","starter"]},{"repository":{"name":"hugo-future-imperfect-slim","url":"https://github.com/pacollins/hugo-future-imperfect-slim","updatedAt":"2020-07-27T00:46:45Z","forks":{"totalCount":120},"stargazers":{"totalCount":154}},"tags":["academic","academicons","blog","contact form","css grid","disqus","fancybox","font awesome","gallery","google analytics","google news","highlight.js","jquery","lunr.js","multilingual","netlify","responsive","search","open graph","staticman","syntax highlighting","twitter cards"]},{"repository":{"name":"airspace-hugo","url":"https://github.com/themefisher/airspace-hugo","updatedAt":"2020-08-01T10:20:30Z","forks":{"totalCount":272},"stargazers":{"totalCount":151}},"tags":["blog","google-analytics","fast","modern","minimal","minimalistic","business","agency-template","white","light","multilingual","bootstrap","company","portfolio","projects","responsive","themefisher"]},{"repository":{"name":"hugo-black-and-light-theme","url":"https://github.com/davidhampgonsalves/hugo-black-and-light-theme","updatedAt":"2020-07-29T13:55:51Z","forks":{"totalCount":70},"stargazers":{"totalCount":150}},"tags":["responsive","minimal","simple","personal","white"]},{"repository":{"name":"hugo-sustain","url":"https://github.com/nurlansu/hugo-sustain","updatedAt":"2020-07-20T13:19:37Z","forks":{"totalCount":94},"stargazers":{"totalCount":148}},"tags":["blog","minimal","responsive"]},{"repository":{"name":"hugo-theme-pure","url":"https://github.com/xiaoheiAh/hugo-theme-pure","updatedAt":"2020-08-01T00:26:49Z","forks":{"totalCount":84},"stargazers":{"totalCount":147}},"tags":["blog","clean","simple","dark","white","search"]},{"repository":{"name":"cupper-hugo-theme","url":"https://github.com/zwbetz-gh/cupper-hugo-theme","updatedAt":"2020-07-30T11:46:48Z","forks":{"totalCount":105},"stargazers":{"totalCount":146}},"tags":["accessible","blog","documentation","dark"]},{"repository":{"name":"lanyon-hugo","url":"https://github.com/tummychow/lanyon-hugo","updatedAt":"2020-07-26T05:49:09Z","forks":{"totalCount":63},"stargazers":{"totalCount":142}},"tags":["blog"]},{"repository":{"name":"hugo-ink","url":"https://github.com/knadh/hugo-ink","updatedAt":"2020-07-30T19:11:19Z","forks":{"totalCount":62},"stargazers":{"totalCount":137}},"tags":["minimal","clean","blog","responsive","personal","simple","minimalist","portfolio","dark"]},{"repository":{"name":"hugo-whisper-theme","url":"https://github.com/JugglerX/hugo-whisper-theme","updatedAt":"2020-07-30T14:12:25Z","forks":{"totalCount":71},"stargazers":{"totalCount":133}},"tags":["documentation","responsive","minimal","clean","bootstrap","zerostatic"]},{"repository":{"name":"hugo-theme-novela","url":"https://github.com/forestryio/hugo-theme-novela","updatedAt":"2020-07-28T05:06:08Z","forks":{"totalCount":72},"stargazers":{"totalCount":130}},"tags":["blog"]},{"repository":{"name":"hugrid","url":"https://github.com/aerohub/hugrid","updatedAt":"2020-07-16T17:02:45Z","forks":{"totalCount":51},"stargazers":{"totalCount":129}},"tags":["responsive","grid","portfolio","cards","simple","collections","google analytics"]},{"repository":{"name":"hugo-resume","url":"https://github.com/eddiewebb/hugo-resume","updatedAt":"2020-07-31T15:32:00Z","forks":{"totalCount":121},"stargazers":{"totalCount":128}},"tags":["portfolio","resume","responsive","cms"]},{"repository":{"name":"dot","url":"https://github.com/themefisher/dot","updatedAt":"2020-07-30T13:09:30Z","forks":{"totalCount":98},"stargazers":{"totalCount":127}},"tags":["documentation","bootstrap","light","minimal","clean","simple","fast","modern","white","customizable","creative","flexbox","minimalistic","highlight.js","typography","docs","material design","highlighting","contact form","responsive","syntax highlighting","multilingual","single page","themefisher"]},{"repository":{"name":"ghostwriter","url":"https://github.com/jbub/ghostwriter","updatedAt":"2020-07-21T14:43:18Z","forks":{"totalCount":124},"stargazers":{"totalCount":126}},"tags":["blog","technical","personal"]},{"repository":{"name":"hugo-theme-pixyll","url":"https://github.com/azmelanar/hugo-theme-pixyll","updatedAt":"2020-07-05T08:43:26Z","forks":{"totalCount":45},"stargazers":{"totalCount":126}},"tags":["blog","personal","search","responsive","minimal"]},{"repository":{"name":"kross-hugo","url":"https://github.com/themefisher/kross-hugo","updatedAt":"2020-07-31T01:39:49Z","forks":{"totalCount":239},"stargazers":{"totalCount":124}},"tags":["landing-page","fast","light","white","modern","themefisher","hugo-theme","hugo-templates","bootstrap","blog","responsive","clean","simple","creative","contact-form","custom-themes","mobile","minimalistic","pages","resume","portfolio","google analytics","customizable","flexbox","presentation","product","theme","typography"]},{"repository":{"name":"KeepIt","url":"https://github.com/Fastbyte01/KeepIt","updatedAt":"2020-07-27T07:29:33Z","forks":{"totalCount":55},"stargazers":{"totalCount":124}},"tags":["blog","minimal","clean","responsive","gallery","dark","theme"]},{"repository":{"name":"aether","url":"https://github.com/josephhutch/aether","updatedAt":"2020-07-31T19:36:19Z","forks":{"totalCount":61},"stargazers":{"totalCount":123}},"tags":["blog","personal","responsive","minimal","simple","clean","modern","technical","syntax highlighting","google analytics","disqus","material design"]},{"repository":{"name":"story","url":"https://github.com/xaprb/story","updatedAt":"2020-08-01T22:19:45Z","forks":{"totalCount":46},"stargazers":{"totalCount":119}},"tags":["blog","presentation","slide","newsletter"]},{"repository":{"name":"hugo-serif-theme","url":"https://github.com/JugglerX/hugo-serif-theme","updatedAt":"2020-08-01T13:16:54Z","forks":{"totalCount":95},"stargazers":{"totalCount":108}},"tags":["responsive","minimal","clean","business","company","bootstrap","zerostatic","personal","google analytics"]},{"repository":{"name":"blank","url":"https://github.com/Vimux/blank","updatedAt":"2020-07-29T16:54:10Z","forks":{"totalCount":58},"stargazers":{"totalCount":107}},"tags":["blog","plain","blank","starter","development"]},{"repository":{"name":"hugo-theme-air","url":"https://github.com/syui/hugo-theme-air","updatedAt":"2020-07-16T10:25:02Z","forks":{"totalCount":44},"stargazers":{"totalCount":105}},"tags":["blog"]},{"repository":{"name":"hugo-theme-minos","url":"https://github.com/carsonip/hugo-theme-minos","updatedAt":"2020-07-26T14:15:45Z","forks":{"totalCount":60},"stargazers":{"totalCount":105}},"tags":["blog","minimal"]},{"repository":{"name":"hugo-nederburg-theme","url":"https://github.com/appernetic/hugo-nederburg-theme","updatedAt":"2020-06-27T08:17:46Z","forks":{"totalCount":86},"stargazers":{"totalCount":103}},"tags":["projects","minimal","responsive","blog"]},{"repository":{"name":"hugo-theme-dream","url":"https://github.com/g1eny0ung/hugo-theme-dream","updatedAt":"2020-07-26T17:43:40Z","forks":{"totalCount":52},"stargazers":{"totalCount":98}},"tags":["flip","masonry layouts","i18n","blog","google-analytics","disqus","responsive","copyright","avatar","motto","social links","creative","personal","light mode","dark mode"]},{"repository":{"name":"hugo-hero-theme","url":"https://github.com/JugglerX/hugo-hero-theme","updatedAt":"2020-08-01T11:36:29Z","forks":{"totalCount":84},"stargazers":{"totalCount":98}},"tags":["responsive","minimal","clean","company","portfolio","bootstrap","zerostatic"]},{"repository":{"name":"hugo-coder-portfolio","url":"https://github.com/naro143/hugo-coder-portfolio","updatedAt":"2020-08-01T16:10:46Z","forks":{"totalCount":54},"stargazers":{"totalCount":98}},"tags":["blog","minimal","minimalist","responsive","simple","clean","personal"]},{"repository":{"name":"hugo-pacman-theme","url":"https://github.com/coderzh/hugo-pacman-theme","updatedAt":"2020-07-30T14:55:13Z","forks":{"totalCount":26},"stargazers":{"totalCount":94}},"tags":["pacman","blog","responsive"]},{"repository":{"name":"hugo-theme-slim","url":"https://github.com/zhe/hugo-theme-slim","updatedAt":"2020-07-27T17:43:45Z","forks":{"totalCount":47},"stargazers":{"totalCount":94}},"tags":["minimal","clean","neat","black white","blog"]},{"repository":{"name":"forty","url":"https://github.com/MarcusVirg/forty","updatedAt":"2020-07-17T22:15:43Z","forks":{"totalCount":97},"stargazers":{"totalCount":94}},"tags":["portfolio","company","contact form","google analytics","blog"]},{"repository":{"name":"hugo-theme-diary","url":"https://github.com/AmazingRise/hugo-theme-diary","updatedAt":"2020-07-30T01:41:35Z","forks":{"totalCount":51},"stargazers":{"totalCount":93}},"tags":["blog"]},{"repository":{"name":"hugo-theme-nix","url":"https://github.com/LordMathis/hugo-theme-nix","updatedAt":"2020-06-26T07:32:07Z","forks":{"totalCount":62},"stargazers":{"totalCount":93}},"tags":["simple","minimal","unix","terminal","blog","multilingual"]},{"repository":{"name":"hugo-devresume-theme","url":"https://github.com/cowboysmall-tools/hugo-devresume-theme","updatedAt":"2020-07-30T09:25:13Z","forks":{"totalCount":48},"stargazers":{"totalCount":93}},"tags":["cv","resume"]},{"repository":{"name":"hugo-theme-techdoc","url":"https://github.com/thingsym/hugo-theme-techdoc","updatedAt":"2020-07-02T20:07:47Z","forks":{"totalCount":78},"stargazers":{"totalCount":92}},"tags":["documentation","docs","responsive","google analytics","table of contents"]},{"repository":{"name":"slate","url":"https://github.com/gesquive/slate","updatedAt":"2020-07-31T23:17:51Z","forks":{"totalCount":39},"stargazers":{"totalCount":91}},"tags":["speed-dial","single-page"]},{"repository":{"name":"Hugo-Octopress","url":"https://github.com/parsiya/Hugo-Octopress","updatedAt":"2020-07-01T00:19:00Z","forks":{"totalCount":35},"stargazers":{"totalCount":89}},"tags":["octopress","hugo"]},{"repository":{"name":"hugo-primer","url":"https://github.com/qqhann/hugo-primer","updatedAt":"2020-07-16T08:46:23Z","forks":{"totalCount":39},"stargazers":{"totalCount":88}},"tags":["blog","simple","minimal","clean","personal","syntax highlighting","white","light","simple page","technical"]},{"repository":{"name":"hugo-theme-noteworthy","url":"https://github.com/kimcc/hugo-theme-noteworthy","updatedAt":"2020-07-28T21:49:44Z","forks":{"totalCount":60},"stargazers":{"totalCount":88}},"tags":["blog","minimalist","minimal","clean","simple","responsive","light"]},{"repository":{"name":"hugo-lithium-theme","url":"https://github.com/jrutheiser/hugo-lithium-theme","updatedAt":"2020-07-29T01:12:45Z","forks":{"totalCount":42},"stargazers":{"totalCount":86}},"tags":["blog"]},{"repository":{"name":"hugo-theme-zen","url":"https://github.com/frjo/hugo-theme-zen","updatedAt":"2020-08-01T01:14:42Z","forks":{"totalCount":31},"stargazers":{"totalCount":85}},"tags":["accessible","multilingual","responsive","blog","search","micro","podcast"]},{"repository":{"name":"hugo-icon","url":"https://github.com/SteveLane/hugo-icon","updatedAt":"2020-07-28T20:55:32Z","forks":{"totalCount":69},"stargazers":{"totalCount":85}},"tags":["icon","responsive","single page","hero","personal","company","agency"]},{"repository":{"name":"timer-hugo","url":"https://github.com/themefisher/timer-hugo","updatedAt":"2020-07-16T09:31:40Z","forks":{"totalCount":82},"stargazers":{"totalCount":84}},"tags":["landing-page","google-analytics","fast","light","white","modern","business","agency-template","themefisher","hugo-theme","hugo-templates","bootstrap","blog","responsive","clean","simple","company","projects","creative","contact-form","custom-themes","mobile","minimalistic","pages"]},{"repository":{"name":"purehugo","url":"https://github.com/dplesca/purehugo","updatedAt":"2020-07-09T23:02:18Z","forks":{"totalCount":61},"stargazers":{"totalCount":84}},"tags":["blog","purecss"]},{"repository":{"name":"hugo-base16-theme","url":"https://github.com/htdvisser/hugo-base16-theme","updatedAt":"2020-07-20T16:18:52Z","forks":{"totalCount":47},"stargazers":{"totalCount":84}},"tags":["blog","syntax highlighting"]},{"repository":{"name":"navigator-hugo","url":"https://github.com/themefisher/navigator-hugo","updatedAt":"2020-07-27T03:25:20Z","forks":{"totalCount":71},"stargazers":{"totalCount":82}},"tags":["landing-page","business","agency-template","multilingual","themefisher","hugo-theme","hugo-templates","bootstrap","blog","responsive","clean","simple","company","projects","dark","creative","contact-form","custom-themes","mobile","flexbox","minimalistic","pages"]},{"repository":{"name":"hugo-identity-theme","url":"https://github.com/aerohub/hugo-identity-theme","updatedAt":"2020-07-24T01:24:54Z","forks":{"totalCount":44},"stargazers":{"totalCount":81}},"tags":["responsive","configurable","profile","card","contact","social","minimal","google analytics"]},{"repository":{"name":"archie","url":"https://github.com/athul/archie","updatedAt":"2020-08-01T18:32:00Z","forks":{"totalCount":31},"stargazers":{"totalCount":79}},"tags":["blog","simple","responsive","minimal","tags","personal","clean","shortcodes"]},{"repository":{"name":"pulp","url":"https://github.com/koirand/pulp","updatedAt":"2020-07-14T14:44:39Z","forks":{"totalCount":45},"stargazers":{"totalCount":79}},"tags":["minimal","blog","simple","light","personal","search"]},{"repository":{"name":"hugo-theme-massively","url":"https://github.com/curtistimson/hugo-theme-massively","updatedAt":"2020-07-19T04:43:54Z","forks":{"totalCount":79},"stargazers":{"totalCount":79}},"tags":["blog","html5up"]},{"repository":{"name":"hugo-theme-codex","url":"https://github.com/jakewies/hugo-theme-codex","updatedAt":"2020-08-01T23:58:39Z","forks":{"totalCount":56},"stargazers":{"totalCount":78}},"tags":["website","starter","blog"]},{"repository":{"name":"toha","url":"https://github.com/hossainemruz/toha","updatedAt":"2020-08-01T07:01:37Z","forks":{"totalCount":54},"stargazers":{"totalCount":78}},"tags":["responsive","blog","portfolio"]},{"repository":{"name":"github-style","url":"https://github.com/MeiK2333/github-style","updatedAt":"2020-08-01T08:00:24Z","forks":{"totalCount":30},"stargazers":{"totalCount":78}},"tags":["blog","google analytics"]},{"repository":{"name":"hugo-theme-anubis","url":"https://github.com/Mitrichius/hugo-theme-anubis","updatedAt":"2020-08-01T17:21:51Z","forks":{"totalCount":38},"stargazers":{"totalCount":77}},"tags":["blog","minimal","simple","clean"]},{"repository":{"name":"mediumish-gohugo-theme","url":"https://github.com/lgaida/mediumish-gohugo-theme","updatedAt":"2020-06-16T14:28:20Z","forks":{"totalCount":65},"stargazers":{"totalCount":77}},"tags":["blog","responsive","personal","minimal","clean","disqus","google analytics"]},{"repository":{"name":"hugo-classic","url":"https://github.com/goodroot/hugo-classic","updatedAt":"2020-07-31T22:13:55Z","forks":{"totalCount":46},"stargazers":{"totalCount":76}},"tags":["minimal","blog","personal","simple","clean","starter","minimalist"]},{"repository":{"name":"newsroom","url":"https://github.com/onweru/newsroom","updatedAt":"2020-07-30T00:15:57Z","forks":{"totalCount":39},"stargazers":{"totalCount":76}},"tags":["blog","simple","dark","minimalist","fast","disqus","syntax highlighting"]},{"repository":{"name":"raditian-free-hugo-theme","url":"https://github.com/radity/raditian-free-hugo-theme","updatedAt":"2020-07-25T16:26:55Z","forks":{"totalCount":60},"stargazers":{"totalCount":76}},"tags":["personal-website","personal","portfolio","single-page","one-page","fast","typography","customizable","mobile","resume","fresh","modern","flexbox","hugo-theme","hugo","bootstrap","responsive","clean","simple","creative","contact form","light","white","custom-design","minimal","minimalistic","minimalist","portfolio","google tag manager","google analytics","customizable","flexbox","starter","theme"]},{"repository":{"name":"hugo-theme-basic","url":"https://github.com/siegerts/hugo-theme-basic","updatedAt":"2020-08-01T21:47:03Z","forks":{"totalCount":39},"stargazers":{"totalCount":76}},"tags":["minimal","tachyons","blog","responsive","syntax highlighting","google analytics","plain","clean","starter","rstats","blogdown"]},{"repository":{"name":"hugo-changelog-theme","url":"https://github.com/jsnjack/hugo-changelog-theme","updatedAt":"2020-07-23T09:43:44Z","forks":{"totalCount":19},"stargazers":{"totalCount":73}},"tags":["changelog"]},{"repository":{"name":"liva-hugo","url":"https://github.com/themefisher/liva-hugo","updatedAt":"2020-07-27T04:57:28Z","forks":{"totalCount":73},"stargazers":{"totalCount":70}},"tags":["landing-page","fast","light","white","modern","themefisher","hugo-theme","hugo-templates","bootstrap","blog","responsive","clean","simple","creative","contact-form","custom-themes","mobile","minimalistic","pages","resume","portfolio","google analytics","customizable","flexbox","presentation","product","theme","typography"]},{"repository":{"name":"anatole","url":"https://github.com/lxndrblz/anatole","updatedAt":"2020-08-01T11:17:40Z","forks":{"totalCount":48},"stargazers":{"totalCount":68}},"tags":["blog","responsive","clean","minimalist"]},{"repository":{"name":"manis-hugo-theme","url":"https://github.com/yursan9/manis-hugo-theme","updatedAt":"2020-06-30T05:18:21Z","forks":{"totalCount":32},"stargazers":{"totalCount":67}},"tags":["blog","personal","minimal","simple","clean","light"]},{"repository":{"name":"hugo-swift-theme","url":"https://github.com/onweru/hugo-swift-theme","updatedAt":"2020-07-30T01:03:33Z","forks":{"totalCount":50},"stargazers":{"totalCount":65}},"tags":["blog","staticman","simple","dark","minimalist","fast","light"]},{"repository":{"name":"hugo-uilite","url":"https://github.com/uicardiodev/hugo-uilite","updatedAt":"2020-07-12T12:46:07Z","forks":{"totalCount":44},"stargazers":{"totalCount":65}},"tags":["minimal","responsive","clean","modern","colors","portfolio","blog","skills","experience","services","uicardio"]},{"repository":{"name":"hugo-theme-zdoc","url":"https://github.com/zzossig/hugo-theme-zdoc","updatedAt":"2020-07-23T14:58:50Z","forks":{"totalCount":26},"stargazers":{"totalCount":64}},"tags":["accessible","multilingual","responsive","documentation","search","simple","light","dark","mobile"]},{"repository":{"name":"hugo-journal","url":"https://github.com/dashdashzako/hugo-journal","updatedAt":"2020-07-05T22:55:40Z","forks":{"totalCount":36},"stargazers":{"totalCount":63}},"tags":["minimalist","reading","blog"]},{"repository":{"name":"castanet","url":"https://github.com/mattstratton/castanet","updatedAt":"2020-07-26T02:09:03Z","forks":{"totalCount":32},"stargazers":{"totalCount":60}},"tags":["podcast","responsive"]},{"repository":{"name":"hallo-hugo","url":"https://github.com/EmielH/hallo-hugo","updatedAt":"2020-07-16T15:08:49Z","forks":{"totalCount":29},"stargazers":{"totalCount":60}},"tags":["minimal","clean","responsive","simple","personal","starter","single page","onepage","font awesome","landing page"]},{"repository":{"name":"parsa-hugo","url":"https://github.com/themefisher/parsa-hugo","updatedAt":"2020-07-29T11:20:28Z","forks":{"totalCount":160},"stargazers":{"totalCount":59}},"tags":["landing-page","fast","light","white","modern","themefisher","hugo-theme","hugo-templates","bootstrap","blog","responsive","clean","simple","creative","contact-form","custom-themes","mobile","minimalistic","pages","resume","portfolio","google analytics","customizable","flexbox","presentation","product","theme","typography"]},{"repository":{"name":"personal-web","url":"https://github.com/bjacquemet/personal-web","updatedAt":"2020-07-22T08:07:21Z","forks":{"totalCount":35},"stargazers":{"totalCount":58}},"tags":["portfolio","blog","post","personal","freelancer","developer"]},{"repository":{"name":"minimal-bootstrap-hugo-theme","url":"https://github.com/zwbetz-gh/minimal-bootstrap-hugo-theme","updatedAt":"2020-07-14T12:56:20Z","forks":{"totalCount":20},"stargazers":{"totalCount":58}},"tags":["minimalist","blog","clean","simple","bootstrap"]},{"repository":{"name":"amperage","url":"https://github.com/asurbernardo/amperage","updatedAt":"2020-07-23T01:15:08Z","forks":{"totalCount":20},"stargazers":{"totalCount":58}},"tags":["blog","personal","responsive","minimal","clean","simple","google analytics","light","multilingual","syntax highlighting","fast","customizable","minimalistic","technical","amp","white","disqus","starter"]},{"repository":{"name":"hugo-refresh","url":"https://github.com/PippoRJ/hugo-refresh","updatedAt":"2020-07-30T18:34:50Z","forks":{"totalCount":37},"stargazers":{"totalCount":57}},"tags":["responsive","blog","light","clean","personal","multilingual","syntax-highlighting"]},{"repository":{"name":"vex-hugo","url":"https://github.com/themefisher/vex-hugo","updatedAt":"2020-07-18T08:12:39Z","forks":{"totalCount":78},"stargazers":{"totalCount":57}},"tags":["onepage","bootstrap","ecommerce","single product","product","themefisher"]},{"repository":{"name":"hugo-bootstrap","url":"https://github.com/mmrath/hugo-bootstrap","updatedAt":"2020-06-27T21:17:58Z","forks":{"totalCount":56},"stargazers":{"totalCount":57}},"tags":["blog","technical","personal"]},{"repository":{"name":"material-design","url":"https://github.com/pdevty/material-design","updatedAt":"2020-06-07T17:02:44Z","forks":{"totalCount":34},"stargazers":{"totalCount":57}},"tags":["blog"]},{"repository":{"name":"devfest-theme-hugo","url":"https://github.com/GDGToulouse/devfest-theme-hugo","updatedAt":"2020-07-18T19:53:01Z","forks":{"totalCount":32},"stargazers":{"totalCount":56}},"tags":["conference","devfest"]},{"repository":{"name":"hugo-theme-console","url":"https://github.com/mrmierzejewski/hugo-theme-console","updatedAt":"2020-07-30T17:33:19Z","forks":{"totalCount":18},"stargazers":{"totalCount":56}},"tags":["blog","gallery","portfolio","console","terminal","clean","personal","minimal","monotone","simple","technical","responsive","mobile","minimalist","retro","animation"]},{"repository":{"name":"nofancy","url":"https://github.com/gizak/nofancy","updatedAt":"2020-07-18T00:01:22Z","forks":{"totalCount":31},"stargazers":{"totalCount":56}},"tags":["blog","personal"]},{"repository":{"name":"avicenna","url":"https://github.com/hadisinaee/avicenna","updatedAt":"2020-07-21T19:23:28Z","forks":{"totalCount":24},"stargazers":{"totalCount":55}},"tags":["academic","personal","minimal","minimalist","clean","responsive","simple","university"]},{"repository":{"name":"simple-a","url":"https://github.com/AlexFinn/simple-a","updatedAt":"2020-07-16T01:06:08Z","forks":{"totalCount":27},"stargazers":{"totalCount":54}},"tags":["alexfinn"]},{"repository":{"name":"hugo-theme-blueberry-detox","url":"https://github.com/allnightgrocery/hugo-theme-blueberry-detox","updatedAt":"2020-07-12T12:54:35Z","forks":{"totalCount":56},"stargazers":{"totalCount":54}},"tags":["blog","minimal","ghost","white"]},{"repository":{"name":"hugo-webslides","url":"https://github.com/RCJacH/hugo-webslides","updatedAt":"2020-06-29T14:55:01Z","forks":{"totalCount":17},"stargazers":{"totalCount":53}},"tags":["slide","presentation","responsive","landing page"]},{"repository":{"name":"hugo-terrassa-theme","url":"https://github.com/danielkvist/hugo-terrassa-theme","updatedAt":"2020-07-27T10:44:36Z","forks":{"totalCount":51},"stargazers":{"totalCount":51}},"tags":["blog","clean","personal","company","google analytics","contact form","mobile","modern","accessibility","font awesome"]},{"repository":{"name":"hugo-lamp","url":"https://github.com/huyb1991/hugo-lamp","updatedAt":"2020-07-31T13:15:57Z","forks":{"totalCount":27},"stargazers":{"totalCount":51}},"tags":["hugo","amp","blog","theme","responsive","static-site-generator"]},{"repository":{"name":"hugo-theme-chunky-poster","url":"https://github.com/puresyntax71/hugo-theme-chunky-poster","updatedAt":"2020-07-24T17:44:50Z","forks":{"totalCount":63},"stargazers":{"totalCount":51}},"tags":["minimal","minimalist","blog","responsive","syntax highlighting","multilingual","minimalist","light"]},{"repository":{"name":"educenter-hugo","url":"https://github.com/themefisher/educenter-hugo","updatedAt":"2020-07-31T07:50:09Z","forks":{"totalCount":140},"stargazers":{"totalCount":50}},"tags":["blog","google-analytics","fast","modern","minimal","minimalistic","business","education","white","light","multilingual","bootstrap","company","portfolio","projects","responsive","themefisher"]},{"repository":{"name":"hugo-flex","url":"https://github.com/de-souza/hugo-flex","updatedAt":"2020-07-08T13:58:20Z","forks":{"totalCount":23},"stargazers":{"totalCount":50}},"tags":["responsive","minimal","flexbox","no-javascript"]},{"repository":{"name":"hugo-theme-bootie-docs","url":"https://github.com/progrhyme/hugo-theme-bootie-docs","updatedAt":"2020-07-23T04:13:03Z","forks":{"totalCount":11},"stargazers":{"totalCount":50}},"tags":["documentation","bootstrap","simple","highlight.js"]},{"repository":{"name":"harbor","url":"https://github.com/matsuyoshi30/harbor","updatedAt":"2020-08-01T03:35:31Z","forks":{"totalCount":16},"stargazers":{"totalCount":49}},"tags":["blog","minimal","simple"]},{"repository":{"name":"hugo-vitae","url":"https://github.com/dataCobra/hugo-vitae","updatedAt":"2020-08-01T15:09:27Z","forks":{"totalCount":23},"stargazers":{"totalCount":48}},"tags":["blog","responsive","clean","simple","light","disqus","mobile","customizable","minimalistic","typography","fontawesome","reading"]},{"repository":{"name":"hugo-xmag","url":"https://github.com/yihui/hugo-xmag","updatedAt":"2020-06-23T02:17:25Z","forks":{"totalCount":29},"stargazers":{"totalCount":48}},"tags":["minimal","magazine","clean","simple","minimalist","blog","responsive","google analytics","syntax highlighting"]},{"repository":{"name":"academia-hugo","url":"https://github.com/themefisher/academia-hugo","updatedAt":"2020-07-30T04:09:15Z","forks":{"totalCount":82},"stargazers":{"totalCount":46}},"tags":["widgets","resume","portfolio","responsive","clean","personal","company","blog","minimal","light","dark","themefisher","multilingual","documentation","landing page","projects","single page","contact form","mobile","gallery","search","presentation","simple","minimalist","starter","modern","one page","customizable","themefisher","technical","product","slide"]},{"repository":{"name":"er","url":"https://github.com/lingxz/er","updatedAt":"2020-06-03T15:41:20Z","forks":{"totalCount":26},"stargazers":{"totalCount":46}},"tags":["responsive","white","blog"]},{"repository":{"name":"papercss-hugo-theme","url":"https://github.com/zwbetz-gh/papercss-hugo-theme","updatedAt":"2020-07-21T16:13:26Z","forks":{"totalCount":27},"stargazers":{"totalCount":45}},"tags":["blog","paper","informal"]},{"repository":{"name":"simplicity","url":"https://github.com/eshlox/simplicity","updatedAt":"2020-07-10T16:03:06Z","forks":{"totalCount":20},"stargazers":{"totalCount":45}},"tags":["blog","responsive","minimal"]},{"repository":{"name":"northendlab-hugo","url":"https://github.com/themefisher/northendlab-hugo","updatedAt":"2020-07-27T17:24:57Z","forks":{"totalCount":104},"stargazers":{"totalCount":44}},"tags":["landing-page","fast","light","white","modern","themefisher","hugo-theme","hugo-templates","bootstrap","blog","responsive","clean","simple","creative","contact-form","custom-themes","mobile","minimalistic","pages","resume","portfolio","google analytics","customizable","flexbox","presentation","product","theme","typography"]},{"repository":{"name":"Binario","url":"https://github.com/Vimux/Binario","updatedAt":"2020-07-20T19:17:52Z","forks":{"totalCount":18},"stargazers":{"totalCount":44}},"tags":["blog","dark","disqus","google analytics","responsive"]},{"repository":{"name":"kraiklyn","url":"https://github.com/jsnjack/kraiklyn","updatedAt":"2020-07-31T04:51:32Z","forks":{"totalCount":29},"stargazers":{"totalCount":44}},"tags":["one page","docs","documentation","simple","minimalistic"]},{"repository":{"name":"hugo-theme-winning","url":"https://github.com/cssandstuff/hugo-theme-winning","updatedAt":"2020-06-02T09:02:46Z","forks":{"totalCount":12},"stargazers":{"totalCount":43}},"tags":["cv","one page"]},{"repository":{"name":"indigo","url":"https://github.com/AngeloStavrow/indigo","updatedAt":"2020-07-26T21:18:46Z","forks":{"totalCount":26},"stargazers":{"totalCount":42}},"tags":["blog","responsive","minimal"]},{"repository":{"name":"hugo-blog-jeffprod","url":"https://github.com/Tazeg/hugo-blog-jeffprod","updatedAt":"2020-07-25T01:18:46Z","forks":{"totalCount":21},"stargazers":{"totalCount":42}},"tags":["simple","blog","theme","pagination","archives","tags","bulma","personal"]},{"repository":{"name":"vanilla-bootstrap-hugo-theme","url":"https://github.com/zwbetz-gh/vanilla-bootstrap-hugo-theme","updatedAt":"2020-07-23T09:45:22Z","forks":{"totalCount":26},"stargazers":{"totalCount":42}},"tags":["home","blog","tags","bootstrap","minimal","clean","simple","feather"]},{"repository":{"name":"vienna","url":"https://github.com/keichi/vienna","updatedAt":"2020-06-20T11:21:35Z","forks":{"totalCount":43},"stargazers":{"totalCount":41}},"tags":["blog","tags","bootstrap"]},{"repository":{"name":"liquorice","url":"https://github.com/eliasson/liquorice","updatedAt":"2020-06-22T11:54:14Z","forks":{"totalCount":18},"stargazers":{"totalCount":40}},"tags":[]},{"repository":{"name":"hugo-dusk","url":"https://github.com/gyorb/hugo-dusk","updatedAt":"2020-07-26T19:23:39Z","forks":{"totalCount":34},"stargazers":{"totalCount":40}},"tags":["blog","responsive","google analytics","disqus","utterances","syntax highlighting","custom themes","minimal","minimalist","clean","dark"]},{"repository":{"name":"slick","url":"https://github.com/spookey/slick","updatedAt":"2020-07-31T08:17:48Z","forks":{"totalCount":14},"stargazers":{"totalCount":39}},"tags":["blog","personal","responsive","mobile","minimal","clean","light","high contrast","typography"]},{"repository":{"name":"hugo-initio","url":"https://github.com/miguelsimoni/hugo-initio","updatedAt":"2020-06-15T08:34:13Z","forks":{"totalCount":74},"stargazers":{"totalCount":39}},"tags":["blog","responsive","personal","google analytics","portfolio","disqus","bootstrap","font awesome","projects","creative","landing page","product","white","share this"]},{"repository":{"name":"erblog","url":"https://github.com/ertuil/erblog","updatedAt":"2020-07-28T01:22:46Z","forks":{"totalCount":20},"stargazers":{"totalCount":36}},"tags":["blog","personal","responsive","mobile","fast","gallery"]},{"repository":{"name":"ace-documentation","url":"https://github.com/vantagedesign/ace-documentation","updatedAt":"2020-07-16T11:31:18Z","forks":{"totalCount":16},"stargazers":{"totalCount":36}},"tags":["documentation","bootstrap","responsive","syntax highlighting","search","google analytics","font awesome","highlight.js","docs","clean","mobile","fast","light","simple","minimal","minimalist"]},{"repository":{"name":"hugo-cards","url":"https://github.com/bul-ikana/hugo-cards","updatedAt":"2020-07-16T17:03:10Z","forks":{"totalCount":35},"stargazers":{"totalCount":36}},"tags":["bootstrap","cards","responsive","jekyll","blog"]},{"repository":{"name":"hugo-theme-w3css-basic","url":"https://github.com/it-gro/hugo-theme-w3css-basic","updatedAt":"2020-07-04T14:07:48Z","forks":{"totalCount":19},"stargazers":{"totalCount":36}},"tags":["blog","company","contact form","custom themes","disqus","font awesome","gallery","google analytics","landing page","mobile","monochromatic","pages","personal","portfolio","products","projects","responsive","search","syntax highlighting","w3css"]},{"repository":{"name":"hugo-shopping-product-catalogue-simple","url":"https://github.com/kishaningithub/hugo-shopping-product-catalogue-simple","updatedAt":"2020-07-29T11:40:10Z","forks":{"totalCount":27},"stargazers":{"totalCount":36}},"tags":["shopping","catalogue","product catalogue","ecommerce","minimal","responsive"]},{"repository":{"name":"hugo-theme-revealjs","url":"https://github.com/RealOrangeOne/hugo-theme-revealjs","updatedAt":"2020-06-26T07:39:34Z","forks":{"totalCount":12},"stargazers":{"totalCount":36}},"tags":["presentation","revealjs"]},{"repository":{"name":"vncnt-hugo","url":"https://github.com/fncnt/vncnt-hugo","updatedAt":"2020-08-01T13:43:25Z","forks":{"totalCount":16},"stargazers":{"totalCount":35}},"tags":["minimal","landingpage","responsive","fontawesome","personal"]},{"repository":{"name":"hugo-theme-vec","url":"https://github.com/IvanChou/hugo-theme-vec","updatedAt":"2020-04-19T17:57:16Z","forks":{"totalCount":25},"stargazers":{"totalCount":35}},"tags":["minimal","clean","neat","black white","blog"]},{"repository":{"name":"hugo-alageek-theme","url":"https://github.com/gkmngrgn/hugo-alageek-theme","updatedAt":"2020-07-08T14:49:02Z","forks":{"totalCount":19},"stargazers":{"totalCount":34}},"tags":["clean","fast","responsive","typography","disqus","light","dark","syntax-highlighting"]},{"repository":{"name":"paperback","url":"https://github.com/dashdashzako/paperback","updatedAt":"2020-07-20T12:34:25Z","forks":{"totalCount":15},"stargazers":{"totalCount":34}},"tags":["minimalist","reading","sepia","blog"]},{"repository":{"name":"hugo-hello-programmer-theme","url":"https://github.com/lubang/hugo-hello-programmer-theme","updatedAt":"2020-06-03T13:17:01Z","forks":{"totalCount":19},"stargazers":{"totalCount":34}},"tags":["blog","hugo","lulab","donggeun","bang","lubang","programmer"]},{"repository":{"name":"hugo-sodium-theme","url":"https://github.com/uicardiodev/hugo-sodium-theme","updatedAt":"2020-07-23T06:33:23Z","forks":{"totalCount":21},"stargazers":{"totalCount":34}},"tags":["minimal","responsive","clean","modern","gradients","portfolio","blog","uicardio"]},{"repository":{"name":"onetwothree","url":"https://github.com/schollz/onetwothree","updatedAt":"2020-07-30T01:09:30Z","forks":{"totalCount":16},"stargazers":{"totalCount":33}},"tags":["minimal","mobile","responsive","elegant"]},{"repository":{"name":"alpha-church","url":"https://github.com/funkydan2/alpha-church","updatedAt":"2020-07-21T03:10:25Z","forks":{"totalCount":38},"stargazers":{"totalCount":32}},"tags":["church","podcast"]},{"repository":{"name":"hugo-lodi-theme","url":"https://github.com/xaviablaza/hugo-lodi-theme","updatedAt":"2020-06-17T19:35:09Z","forks":{"totalCount":30},"stargazers":{"totalCount":32}},"tags":["lodi","responsive","hero","personal","portfolio","case study","ux"]},{"repository":{"name":"solar-theme-hugo","url":"https://github.com/bake/solar-theme-hugo","updatedAt":"2020-07-22T06:48:24Z","forks":{"totalCount":24},"stargazers":{"totalCount":31}},"tags":["blog","light","dark","responsive","solarized"]},{"repository":{"name":"restaurant-hugo","url":"https://github.com/themefisher/restaurant-hugo","updatedAt":"2020-07-27T03:31:27Z","forks":{"totalCount":31},"stargazers":{"totalCount":30}},"tags":["landing-page","fast","light","white","modern","business","agency-template","themefisher","hugo-theme","hugo-templates","bootstrap","blog","responsive","clean","simple","company","projects","creative","contact-form","custom-themes","mobile","minimalistic","pages"]},{"repository":{"name":"charaka-hugo-theme","url":"https://github.com/natarajmb/charaka-hugo-theme","updatedAt":"2020-07-14T13:00:11Z","forks":{"totalCount":28},"stargazers":{"totalCount":30}},"tags":["personal","blog","simple","clean","minimalist","highlight.js","jssocials","font-awesome","bluma"]},{"repository":{"name":"grid-side","url":"https://github.com/chipsenkbeil/grid-side","updatedAt":"2020-06-26T07:40:11Z","forks":{"totalCount":24},"stargazers":{"totalCount":30}},"tags":["blog","portfolio","projects","gallery"]},{"repository":{"name":"hugonews","url":"https://github.com/spaghettiwews/hugonews","updatedAt":"2020-07-10T02:43:25Z","forks":{"totalCount":7},"stargazers":{"totalCount":29}},"tags":["bookmarking","minimal","clean"]},{"repository":{"name":"internet-weblog","url":"https://github.com/jnjosh/internet-weblog","updatedAt":"2020-07-23T07:12:27Z","forks":{"totalCount":22},"stargazers":{"totalCount":29}},"tags":["blog","personal","minimal","microblog","photoblog","linkblog","responsive"]},{"repository":{"name":"bare-hugo-theme","url":"https://github.com/orf/bare-hugo-theme","updatedAt":"2020-08-01T16:57:37Z","forks":{"totalCount":16},"stargazers":{"totalCount":28}},"tags":["blog","responsive","minimal","clean","simple","google-analytics","light","fast","flexbox","bulma"]},{"repository":{"name":"hugo-split-theme","url":"https://github.com/escalate/hugo-split-theme","updatedAt":"2020-06-29T20:06:34Z","forks":{"totalCount":47},"stargazers":{"totalCount":28}},"tags":["minimal","onepage","one page","responsive","personal"]},{"repository":{"name":"bootstrap-bp-hugo-theme","url":"https://github.com/spech66/bootstrap-bp-hugo-theme","updatedAt":"2020-05-10T09:53:00Z","forks":{"totalCount":13},"stargazers":{"totalCount":28}},"tags":["minimalist","minimal","blog","clean","simple","bootstrap","responsive","google analytics","syntax sighlighting","light","fast","dark","pages","font awesome","fontawesome","multilingual","customizable","mobile"]},{"repository":{"name":"bootstrap-bp-hugo-startpage","url":"https://github.com/spech66/bootstrap-bp-hugo-startpage","updatedAt":"2020-07-16T17:02:36Z","forks":{"totalCount":10},"stargazers":{"totalCount":28}},"tags":["minimalist","single-page","clean","simple","bootstrap","responsive","google analytics","one-page","light","fast"]},{"repository":{"name":"edidor","url":"https://github.com/jacobsun/edidor","updatedAt":"2020-05-12T21:11:25Z","forks":{"totalCount":8},"stargazers":{"totalCount":28}},"tags":["blog","editor","edidor"]},{"repository":{"name":"hugo-conference","url":"https://github.com/jweslley/hugo-conference","updatedAt":"2020-07-29T09:22:30Z","forks":{"totalCount":18},"stargazers":{"totalCount":28}},"tags":["conference","responsive","l10n","google-analytics"]},{"repository":{"name":"hugo-lime","url":"https://github.com/uicardiodev/hugo-lime","updatedAt":"2020-07-21T07:01:06Z","forks":{"totalCount":18},"stargazers":{"totalCount":28}},"tags":["minimal","blog","services","responsive","bootstrap","uicardio","illustrations"]},{"repository":{"name":"compose","url":"https://github.com/onweru/compose","updatedAt":"2020-07-29T13:13:33Z","forks":{"totalCount":9},"stargazers":{"totalCount":27}},"tags":["simple","docs","dark","customizable","search"]},{"repository":{"name":"Influencer-hugo","url":"https://github.com/themefisher/Influencer-hugo","updatedAt":"2020-07-28T22:04:26Z","forks":{"totalCount":26},"stargazers":{"totalCount":27}},"tags":["ecommerce","bootstrap","blog","contact","responsive","gethugothemes","clean","single product","minimal","light","google analytics","mobile","fast","customizable","white","flex","pages","hugo themes","hugo templates","netlify","themefisher","one page"]},{"repository":{"name":"etch","url":"https://github.com/LukasJoswiak/etch","updatedAt":"2020-07-22T13:57:12Z","forks":{"totalCount":18},"stargazers":{"totalCount":27}},"tags":["simple","minimal","clean","fast","blog","responsive","dark mode","privacy"]},{"repository":{"name":"ramium","url":"https://github.com/rafed/ramium","updatedAt":"2020-07-30T22:25:25Z","forks":{"totalCount":15},"stargazers":{"totalCount":27}},"tags":["blog","responsive","google analytics","disqus","chords","google search","bulma","fast","social media share","code","math equations","seo"]},{"repository":{"name":"hugo-travelify-theme","url":"https://github.com/balaramadurai/hugo-travelify-theme","updatedAt":"2020-06-13T21:52:16Z","forks":{"totalCount":18},"stargazers":{"totalCount":27}},"tags":["syntax highlighting","rss","widgets","google analytics","responsive","carousel","slider"]},{"repository":{"name":"somrat","url":"https://github.com/somratpro/somrat","updatedAt":"2020-07-26T13:01:58Z","forks":{"totalCount":37},"stargazers":{"totalCount":27}},"tags":["landing-page","fast","light","white","modern","dark","hugo-theme","hugo-templates","bootstrap","blog","responsive","clean","simple","creative","contact-form","custom-themes","mobile","minimalistic","pages","resume","portfolio","google analytics","customizable","flexbox","presentation","product","theme","typography"]},{"repository":{"name":"infinity-hugo","url":"https://github.com/themefisher/infinity-hugo","updatedAt":"2020-07-17T04:43:03Z","forks":{"totalCount":27},"stargazers":{"totalCount":26}},"tags":["comming-soon","landing-page","themefisher","hugo-theme","hugo-templates","bootstrap4"]},{"repository":{"name":"axiom","url":"https://github.com/marketempower/axiom","updatedAt":"2020-07-31T22:42:47Z","forks":{"totalCount":6},"stargazers":{"totalCount":25}},"tags":["seo","organic-search","structured-data","cdn","cloudinary","netlify","jamstack","responsive-images","pagespeed-95","sharing","atom-feed","npm-scripts","custom-css","custom-js","blog","chroma","modular","fast","responsive","tailwindcss","alpinejs","seo"]},{"repository":{"name":"hargo","url":"https://github.com/themefisher/hargo","updatedAt":"2020-07-30T09:24:57Z","forks":{"totalCount":58},"stargazers":{"totalCount":25}},"tags":["ecommerce","bootstrap","blog","contact","responsive","gethugothemes","clean","single product","minimal","light","google analytics","disqus","mobile","fast","customizable","white","flex","pages","hugo themes","hugo templates","netlify","themefisher"]},{"repository":{"name":"smol","url":"https://github.com/colorchestra/smol","updatedAt":"2020-07-31T02:52:22Z","forks":{"totalCount":7},"stargazers":{"totalCount":24}},"tags":["blog","minimal","monospace","dark mode","simple","clean","light","responsive","fast","no-js","no-tracking","privacy"]},{"repository":{"name":"gochowdown","url":"https://github.com/seanlane/gochowdown","updatedAt":"2020-08-01T11:28:34Z","forks":{"totalCount":26},"stargazers":{"totalCount":24}},"tags":["recipes","cooking","responsive","clean"]},{"repository":{"name":"roxo-hugo","url":"https://github.com/StaticMania/roxo-hugo","updatedAt":"2020-07-22T01:17:59Z","forks":{"totalCount":20},"stargazers":{"totalCount":24}},"tags":["clean","minimal","agency","corporate","creative agency","creative studio","portfolio","staticmania","responsive","blog","customizable","company","creative","agency template"]},{"repository":{"name":"crab","url":"https://github.com/thomasheller/crab","updatedAt":"2020-07-22T18:42:54Z","forks":{"totalCount":20},"stargazers":{"totalCount":24}},"tags":["clean"]},{"repository":{"name":"allegiant","url":"https://github.com/brycematheson/allegiant","updatedAt":"2020-06-23T16:13:38Z","forks":{"totalCount":14},"stargazers":{"totalCount":24}},"tags":["blog","hugo","allegiant"]},{"repository":{"name":"polymer","url":"https://github.com/pdevty/polymer","updatedAt":"2020-04-10T11:21:28Z","forks":{"totalCount":15},"stargazers":{"totalCount":24}},"tags":["blog"]},{"repository":{"name":"hugo-kiera","url":"https://github.com/funkydan2/hugo-kiera","updatedAt":"2020-07-30T23:24:10Z","forks":{"totalCount":24},"stargazers":{"totalCount":23}},"tags":["blog","minimal","responsive"]},{"repository":{"name":"devise","url":"https://github.com/austingebauer/devise","updatedAt":"2020-07-28T00:55:20Z","forks":{"totalCount":8},"stargazers":{"totalCount":23}},"tags":["blog","minimal","personal","simple","clean"]},{"repository":{"name":"hugo-highlights-theme","url":"https://github.com/schmanat/hugo-highlights-theme","updatedAt":"2020-07-06T00:11:18Z","forks":{"totalCount":17},"stargazers":{"totalCount":23}},"tags":["portfolio","onepage","one page","contact form","google analytics"]},{"repository":{"name":"hugo-tailwind-journal","url":"https://github.com/ianrodrigues/hugo-tailwind-journal","updatedAt":"2020-07-31T21:18:13Z","forks":{"totalCount":4},"stargazers":{"totalCount":23}},"tags":["minimalist","reading","blog","tailwindcss"]},{"repository":{"name":"cayman-hugo-theme","url":"https://github.com/zwbetz-gh/cayman-hugo-theme","updatedAt":"2020-06-20T16:03:52Z","forks":{"totalCount":22},"stargazers":{"totalCount":22}},"tags":["blog","clean","color configuration"]},{"repository":{"name":"inkblotty","url":"https://github.com/tosi29/inkblotty","updatedAt":"2020-06-26T01:43:53Z","forks":{"totalCount":18},"stargazers":{"totalCount":22}},"tags":["blog","responsive","wordpress","disqus","google analytics"]},{"repository":{"name":"strange-case","url":"https://github.com/ExchangeRate-API/strange-case","updatedAt":"2020-02-25T16:02:40Z","forks":{"totalCount":23},"stargazers":{"totalCount":22}},"tags":["blog","responsive","minimal","simple","clean","bootstrap"]},{"repository":{"name":"hugo-material-blog","url":"https://github.com/Xzya/hugo-material-blog","updatedAt":"2019-09-03T14:11:41Z","forks":{"totalCount":16},"stargazers":{"totalCount":22}},"tags":["blog","material design","multilingual","clean","google analytics","responsive"]},{"repository":{"name":"hugo-stellar-theme","url":"https://github.com/antonpolishko/hugo-stellar-theme","updatedAt":"2020-07-27T07:56:24Z","forks":{"totalCount":18},"stargazers":{"totalCount":22}},"tags":[]},{"repository":{"name":"hugo-theme-den","url":"https://github.com/shaform/hugo-theme-den","updatedAt":"2020-07-17T03:12:17Z","forks":{"totalCount":15},"stargazers":{"totalCount":21}},"tags":["responsive","blog","clean","multilingual"]},{"repository":{"name":"hugo-piercer-theme","url":"https://github.com/danielkvist/hugo-piercer-theme","updatedAt":"2020-04-18T02:08:11Z","forks":{"totalCount":11},"stargazers":{"totalCount":21}},"tags":["blog","responsive","minimal","simple","font awesome","dark","landing page","contact form","mobile","fast","customizable","google fonts"]},{"repository":{"name":"hugo-casper3","url":"https://github.com/jonathanjanssens/hugo-casper3","updatedAt":"2020-07-21T07:13:56Z","forks":{"totalCount":16},"stargazers":{"totalCount":20}},"tags":["blog","dark","light"]},{"repository":{"name":"twentyfourteen","url":"https://github.com/jaden/twentyfourteen","updatedAt":"2020-02-15T11:48:42Z","forks":{"totalCount":12},"stargazers":{"totalCount":20}},"tags":["blog","wordpress"]},{"repository":{"name":"hugo_eiio","url":"https://github.com/leonhe/hugo_eiio","updatedAt":"2020-07-26T05:45:02Z","forks":{"totalCount":2},"stargazers":{"totalCount":19}},"tags":["blog","minimal","clean","simple","bootstrap","personal","mobile"]},{"repository":{"name":"soho","url":"https://github.com/alexandrevicenzi/soho","updatedAt":"2020-07-29T03:48:27Z","forks":{"totalCount":18},"stargazers":{"totalCount":19}},"tags":["blog","responsive","clean","minimalist"]},{"repository":{"name":"aafu","url":"https://github.com/darshanbaral/aafu","updatedAt":"2020-07-23T09:46:26Z","forks":{"totalCount":24},"stargazers":{"totalCount":19}},"tags":["portfolio","accordion","resume","blog"]},{"repository":{"name":"hugograyscale","url":"https://github.com/runningstream/hugograyscale","updatedAt":"2020-05-17T04:40:46Z","forks":{"totalCount":27},"stargazers":{"totalCount":19}},"tags":["minimal","simple","landing-page","one-page","responsive","accessible","company"]},{"repository":{"name":"hugo-theme-dopetrope","url":"https://github.com/curtistimson/hugo-theme-dopetrope","updatedAt":"2020-06-26T07:39:04Z","forks":{"totalCount":14},"stargazers":{"totalCount":19}},"tags":["blog","html5up"]},{"repository":{"name":"hestia-pure","url":"https://github.com/diwao/hestia-pure","updatedAt":"2020-01-28T02:35:57Z","forks":{"totalCount":8},"stargazers":{"totalCount":19}},"tags":[]},{"repository":{"name":"hugo-faq-theme","url":"https://github.com/aerohub/hugo-faq-theme","updatedAt":"2020-03-07T12:34:50Z","forks":{"totalCount":10},"stargazers":{"totalCount":19}},"tags":["faq","data files"]},{"repository":{"name":"silhouette-hugo","url":"https://github.com/mattbutton/silhouette-hugo","updatedAt":"2020-05-04T13:09:52Z","forks":{"totalCount":13},"stargazers":{"totalCount":18}},"tags":["blog, responsive, personal, bootstrap, disqus, google analytics, syntax highligting, font awesome, landing page, flexbox"]},{"repository":{"name":"onepress","url":"https://github.com/ijsucceed/onepress","updatedAt":"2019-10-26T03:25:17Z","forks":{"totalCount":4},"stargazers":{"totalCount":18}},"tags":["responsive","disqus","widgets","blog","fontawesome","minimal"]},{"repository":{"name":"hpstr-hugo-theme","url":"https://github.com/dldx/hpstr-hugo-theme","updatedAt":"2020-03-22T16:52:48Z","forks":{"totalCount":17},"stargazers":{"totalCount":18}},"tags":["responsive","blog"]},{"repository":{"name":"simple-style","url":"https://github.com/yanlinlin82/simple-style","updatedAt":"2020-08-01T09:44:01Z","forks":{"totalCount":8},"stargazers":{"totalCount":17}},"tags":["simple","blog","white"]},{"repository":{"name":"yourfolio","url":"https://github.com/serg/yourfolio","updatedAt":"2020-07-19T23:28:06Z","forks":{"totalCount":12},"stargazers":{"totalCount":17}},"tags":["responsive","minimal","simple","personal","portfolio"]},{"repository":{"name":"hugo-theme-lean-launch-page","url":"https://github.com/felicianotech/hugo-theme-lean-launch-page","updatedAt":"2020-08-01T05:40:18Z","forks":{"totalCount":14},"stargazers":{"totalCount":17}},"tags":["simple","launch page","single page","landing-page"]},{"repository":{"name":"min_night","url":"https://github.com/nathancday/min_night","updatedAt":"2020-05-08T21:26:50Z","forks":{"totalCount":16},"stargazers":{"totalCount":17}},"tags":["blog","night-mode"]},{"repository":{"name":"potato-dark","url":"https://github.com/surajmandalcell/potato-dark","updatedAt":"2020-06-21T20:01:11Z","forks":{"totalCount":8},"stargazers":{"totalCount":17}},"tags":["responsive","blog","google analytics","disqus","clean","tags","minimal","minimalist","simple","white","starter"]},{"repository":{"name":"hugo-theme-yuki","url":"https://github.com/iCyris/hugo-theme-yuki","updatedAt":"2020-04-15T21:53:37Z","forks":{"totalCount":8},"stargazers":{"totalCount":17}},"tags":["blog","responsive","highlight","clean"]},{"repository":{"name":"hugo-w3-simple","url":"https://github.com/jesselau76/hugo-w3-simple","updatedAt":"2020-06-05T08:51:16Z","forks":{"totalCount":17},"stargazers":{"totalCount":17}},"tags":["minimal","blog","search","clean","simple","starter","minimalist","responsive","disqus","font-awesome","syntax highlighting","multilingual","google analytics"]},{"repository":{"name":"twenty-twenty-hugo","url":"https://github.com/themefisher/twenty-twenty-hugo","updatedAt":"2020-07-21T17:15:49Z","forks":{"totalCount":24},"stargazers":{"totalCount":16}},"tags":["landing-page","fast","light","white","modern","themefisher","hugo-theme","hugo-templates","bootstrap","blog","responsive","clean","simple","creative","custom-themes","mobile","minimalistic","pages","resume","wordpress","portfolio","google analytics","customizable","flexbox","presentation","product","theme","typography"]},{"repository":{"name":"minimage","url":"https://github.com/d-kusk/minimage","updatedAt":"2020-02-01T13:29:39Z","forks":{"totalCount":10},"stargazers":{"totalCount":16}},"tags":["responsive","simple"]},{"repository":{"name":"hugo-startpage-theme","url":"https://github.com/whi-tw/hugo-startpage-theme","updatedAt":"2020-07-05T08:18:36Z","forks":{"totalCount":7},"stargazers":{"totalCount":16}},"tags":["speed-dial","single-page","material-design","responsive","one-page","offline"]},{"repository":{"name":"anybodyhome","url":"https://github.com/lasseborly/anybodyhome","updatedAt":"2019-08-27T16:55:59Z","forks":{"totalCount":7},"stargazers":{"totalCount":16}},"tags":["clean","simple"]},{"repository":{"name":"paperesque","url":"https://github.com/capnfabs/paperesque","updatedAt":"2020-07-31T10:30:52Z","forks":{"totalCount":3},"stargazers":{"totalCount":15}},"tags":["blog","personal","light","responsive","minimal"]},{"repository":{"name":"hugo-theme-dimension","url":"https://github.com/your-identity/hugo-theme-dimension","updatedAt":"2020-07-21T22:21:17Z","forks":{"totalCount":20},"stargazers":{"totalCount":15}},"tags":["blog","clean","customizable","dark","highlighting","minimal","personal","responsive","simple"]},{"repository":{"name":"contrast-hugo","url":"https://github.com/niklasbuschmann/contrast-hugo","updatedAt":"2020-07-10T16:06:11Z","forks":{"totalCount":17},"stargazers":{"totalCount":15}},"tags":["blog"]},{"repository":{"name":"arabica","url":"https://github.com/nirocfz/arabica","updatedAt":"2020-06-13T14:56:19Z","forks":{"totalCount":21},"stargazers":{"totalCount":15}},"tags":["blog","minimal"]},{"repository":{"name":"elephants","url":"https://github.com/meibenny/elephants","updatedAt":"2020-07-31T15:25:13Z","forks":{"totalCount":11},"stargazers":{"totalCount":15}},"tags":["blog"]},{"repository":{"name":"hugo-theme-tokiwa","url":"https://github.com/heyeshuang/hugo-theme-tokiwa","updatedAt":"2020-07-21T18:16:24Z","forks":{"totalCount":2},"stargazers":{"totalCount":14}},"tags":["minimal","website","responsive","blog"]},{"repository":{"name":"simpleit-hugo-theme","url":"https://github.com/marcanuy/simpleit-hugo-theme","updatedAt":"2020-07-22T14:58:58Z","forks":{"totalCount":2},"stargazers":{"totalCount":14}},"tags":["responsive","bootstrap","font awesome"]},{"repository":{"name":"hugo-now","url":"https://github.com/mikeblum/hugo-now","updatedAt":"2020-05-23T23:41:25Z","forks":{"totalCount":7},"stargazers":{"totalCount":14}},"tags":["blog","profile","jekyll-now","bootstrap","font awesome","responsive","pygments"]},{"repository":{"name":"stip-hugo","url":"https://github.com/EmielH/stip-hugo","updatedAt":"2020-07-16T10:26:43Z","forks":{"totalCount":14},"stargazers":{"totalCount":14}},"tags":["minimal","clean","responsive","simple","personal","starter","single page","onepage","font awesome","landing page"]},{"repository":{"name":"hugo-sugoi","url":"https://github.com/aanupam23/hugo-sugoi","updatedAt":"2020-07-21T16:11:15Z","forks":{"totalCount":7},"stargazers":{"totalCount":13}},"tags":["responsive","minimal","blog","modern","clean","customizable"]},{"repository":{"name":"capsule","url":"https://github.com/sudorook/capsule","updatedAt":"2020-07-16T02:34:08Z","forks":{"totalCount":10},"stargazers":{"totalCount":13}},"tags":["hugo","bulma","css only","font awesome","responsive"]},{"repository":{"name":"hugo-rocinante","url":"https://github.com/mavidser/hugo-rocinante","updatedAt":"2020-07-25T18:26:19Z","forks":{"totalCount":7},"stargazers":{"totalCount":13}},"tags":["blog","minimal","simple","clean","gallery"]},{"repository":{"name":"sada","url":"https://github.com/darshanbaral/sada","updatedAt":"2020-07-30T20:32:27Z","forks":{"totalCount":8},"stargazers":{"totalCount":13}},"tags":["portfolio","resume","simple","onepage"]},{"repository":{"name":"BeyondNothing","url":"https://github.com/salcan/BeyondNothing","updatedAt":"2020-05-27T01:44:09Z","forks":{"totalCount":9},"stargazers":{"totalCount":13}},"tags":["blog","lander","minimalist","clean"]},{"repository":{"name":"hugo-clarity","url":"https://github.com/chipzoller/hugo-clarity","updatedAt":"2020-07-31T15:20:14Z","forks":{"totalCount":2},"stargazers":{"totalCount":12}},"tags":["blog","technical","simple","dark","syntax highlighting"]},{"repository":{"name":"hugo-theme-iris","url":"https://github.com/peaceiris/hugo-theme-iris","updatedAt":"2020-07-28T02:26:57Z","forks":{"totalCount":8},"stargazers":{"totalCount":12}},"tags":["blog","responsive","personal","google-analytics","portfolio","dark","disqus","multilingual","fast","mobile","syntax-highlighting","flexbox","presentation","bulma","netlify","slide"]},{"repository":{"name":"hugo-theme-mixedpaper","url":"https://github.com/wayjam/hugo-theme-mixedpaper","updatedAt":"2020-07-23T07:40:43Z","forks":{"totalCount":12},"stargazers":{"totalCount":12}},"tags":["blog","minimalist","paper","clean","simple","light","writing"]},{"repository":{"name":"foundation-theme","url":"https://github.com/hdcdstr8fwd/foundation-theme","updatedAt":"2020-01-26T01:17:14Z","forks":{"totalCount":10},"stargazers":{"totalCount":12}},"tags":["hugo","foundation"]},{"repository":{"name":"hugo_theme_adam_eve","url":"https://github.com/blankoworld/hugo_theme_adam_eve","updatedAt":"2020-07-22T20:17:06Z","forks":{"totalCount":6},"stargazers":{"totalCount":11}},"tags":["minimal","wiki-like","documentation"]},{"repository":{"name":"hugo-theme-tony","url":"https://github.com/ThemeTony/hugo-theme-tony","updatedAt":"2020-07-18T13:19:25Z","forks":{"totalCount":0},"stargazers":{"totalCount":11}},"tags":["simple","elegant","transportation","porting"]},{"repository":{"name":"photo-grid","url":"https://github.com/Chen-Zhe/photo-grid","updatedAt":"2020-08-01T12:46:42Z","forks":{"totalCount":6},"stargazers":{"totalCount":11}},"tags":["gallery","photography","content management","google analytics"]},{"repository":{"name":"darksimplicity","url":"https://github.com/kritoke/darksimplicity","updatedAt":"2020-06-20T01:53:34Z","forks":{"totalCount":4},"stargazers":{"totalCount":11}},"tags":["blog","dark","minimalist"]},{"repository":{"name":"hugo-spectre-pixel-theme","url":"https://github.com/st-wong/hugo-spectre-pixel-theme","updatedAt":"2020-07-23T15:15:47Z","forks":{"totalCount":11},"stargazers":{"totalCount":11}},"tags":["modern design","timeline","blog","portfolio","resume","responsive","pixel","font awesome","spectre css framework","devicon","google analytics","rss","syntax highlighting","pagination"]},{"repository":{"name":"lekh","url":"https://github.com/invinciblycool/lekh","updatedAt":"2020-07-15T11:58:17Z","forks":{"totalCount":3},"stargazers":{"totalCount":10}},"tags":["minimal","clean","blog","responsive","personal","simple","minimalist","portfolio","text-focussed","dark","dark-mode","rss"]},{"repository":{"name":"materialize-bp-hugo-theme","url":"https://github.com/spech66/materialize-bp-hugo-theme","updatedAt":"2020-06-18T12:48:21Z","forks":{"totalCount":4},"stargazers":{"totalCount":10}},"tags":["minimalist","minimal","blog","clean","simple","material design","responsive","google analytics","syntax sighlighting","light","fast","dark","pages","font awesome","fontawesome","flexbox","multilingual","customizable","mobile"]},{"repository":{"name":"hugo-apps-theme","url":"https://github.com/gonnux/hugo-apps-theme","updatedAt":"2020-03-08T20:11:58Z","forks":{"totalCount":6},"stargazers":{"totalCount":10}},"tags":["minimal","highlight.js","customizable","projects","portfolio","google analytics","syntax highlighting","light","google adsense"]},{"repository":{"name":"Blogpaper","url":"https://github.com/NormandErwan/Blogpaper","updatedAt":"2020-07-16T11:54:04Z","forks":{"totalCount":7},"stargazers":{"totalCount":10}},"tags":["theme","hugo","blog","minimalist","graphical"]},{"repository":{"name":"hugo-business-frontpage-theme","url":"https://github.com/cowboysmall-tools/hugo-business-frontpage-theme","updatedAt":"2020-07-25T15:20:29Z","forks":{"totalCount":11},"stargazers":{"totalCount":10}},"tags":["starter","business","home","page"]},{"repository":{"name":"hugo-theme-wave","url":"https://github.com/syui/hugo-theme-wave","updatedAt":"2019-08-18T11:01:10Z","forks":{"totalCount":7},"stargazers":{"totalCount":10}},"tags":["blog"]},{"repository":{"name":"hugo-theme-doors","url":"https://github.com/zzzmisa/hugo-theme-doors","updatedAt":"2020-05-03T19:55:57Z","forks":{"totalCount":7},"stargazers":{"totalCount":9}},"tags":["single page","onepage","one page","amp","mobile","google-analytics","projects","portfolio"]},{"repository":{"name":"hugo-theme-easybook","url":"https://github.com/Y4er/hugo-theme-easybook","updatedAt":"2020-05-31T12:20:42Z","forks":{"totalCount":6},"stargazers":{"totalCount":9}},"tags":["hugo","simple"]},{"repository":{"name":"hugo-starter","url":"https://github.com/jimfrenette/hugo-starter","updatedAt":"2020-07-15T11:42:37Z","forks":{"totalCount":5},"stargazers":{"totalCount":9}},"tags":["starter","minimal","development","website","responsive","blog"]},{"repository":{"name":"hugo-fabric","url":"https://github.com/wd/hugo-fabric","updatedAt":"2020-05-28T07:33:45Z","forks":{"totalCount":4},"stargazers":{"totalCount":9}},"tags":["blog","archives","tags"]},{"repository":{"name":"hugo-bingo","url":"https://github.com/gundamew/hugo-bingo","updatedAt":"2019-08-20T02:39:56Z","forks":{"totalCount":8},"stargazers":{"totalCount":9}},"tags":["minimalist","simple","clean","blog","starter","responsive"]},{"repository":{"name":"hugo-dusky-neon-potato","url":"https://github.com/VVelox/hugo-dusky-neon-potato","updatedAt":"2020-06-29T07:06:07Z","forks":{"totalCount":3},"stargazers":{"totalCount":9}},"tags":["responsive","blog","google analytics","disqus","clean","tags","minimal","custom themes","minimalist","simple","pink","green","starter","dark","sortable tables"]},{"repository":{"name":"mero","url":"https://github.com/darshanbaral/mero","updatedAt":"2020-07-06T06:20:45Z","forks":{"totalCount":6},"stargazers":{"totalCount":9}},"tags":["personal","blog","dark"]},{"repository":{"name":"hugo-myportfolio-theme","url":"https://github.com/2-REC/hugo-myportfolio-theme","updatedAt":"2020-07-25T08:35:49Z","forks":{"totalCount":9},"stargazers":{"totalCount":8}},"tags":["portfolio","blog","responsive","personal","business","projects","bootstrap"]},{"repository":{"name":"hugo-theme-hamburg","url":"https://github.com/hauke96/hugo-theme-hamburg","updatedAt":"2020-05-18T09:19:30Z","forks":{"totalCount":8},"stargazers":{"totalCount":8}},"tags":["blog","tags","bootstrap","multilingual","clean","minimal","disqus","font awesome","mobile"]},{"repository":{"name":"npq-hugo","url":"https://github.com/ahmedsaadxyzz/npq-hugo","updatedAt":"2020-07-29T22:07:20Z","forks":{"totalCount":9},"stargazers":{"totalCount":8}},"tags":["blog","contact form","micro blog","responsive","mobile","personal","dark"]},{"repository":{"name":"twentynineteen-hugo","url":"https://github.com/jeremybise/twentynineteen-hugo","updatedAt":"2020-03-13T20:13:24Z","forks":{"totalCount":6},"stargazers":{"totalCount":8}},"tags":["blog","clean","light","color configuration","search"]},{"repository":{"name":"hugo-theme-okayish-blog","url":"https://github.com/kongdivin/hugo-theme-okayish-blog","updatedAt":"2020-07-28T10:21:11Z","forks":{"totalCount":2},"stargazers":{"totalCount":7}},"tags":["blog","responsive","i18n"]},{"repository":{"name":"HugoTeX","url":"https://github.com/7ma7X/HugoTeX","updatedAt":"2020-07-27T00:15:07Z","forks":{"totalCount":4},"stargazers":{"totalCount":7}},"tags":["blog","minimal","simple","latex"]},{"repository":{"name":"kitab","url":"https://github.com/darshanbaral/kitab","updatedAt":"2020-06-19T02:44:30Z","forks":{"totalCount":6},"stargazers":{"totalCount":7}},"tags":["book"]},{"repository":{"name":"docter","url":"https://github.com/edavidaja/docter","updatedAt":"2020-05-20T19:32:59Z","forks":{"totalCount":3},"stargazers":{"totalCount":7}},"tags":["documentation","blog"]},{"repository":{"name":"OneDly-Theme","url":"https://github.com/cdeck3r/OneDly-Theme","updatedAt":"2020-07-12T22:10:31Z","forks":{"totalCount":7},"stargazers":{"totalCount":7}},"tags":["documentation","landing page","opensource","single page"]},{"repository":{"name":"hugo-frais","url":"https://github.com/the2ne/hugo-frais","updatedAt":"2020-01-15T20:59:04Z","forks":{"totalCount":7},"stargazers":{"totalCount":7}},"tags":["blog","minimal","responsive"]},{"repository":{"name":"Niello","url":"https://github.com/guangmean/Niello","updatedAt":"2020-03-13T20:13:05Z","forks":{"totalCount":5},"stargazers":{"totalCount":7}},"tags":["blog","syntax highlighting","highlight.js","dark"]},{"repository":{"name":"hugo-frances-theme","url":"https://github.com/mcrwfrd/hugo-frances-theme","updatedAt":"2020-06-19T08:18:50Z","forks":{"totalCount":5},"stargazers":{"totalCount":7}},"tags":["grid","portfolio"]},{"repository":{"name":"hugo-grapes","url":"https://github.com/shankar/hugo-grapes","updatedAt":"2019-09-27T06:56:03Z","forks":{"totalCount":8},"stargazers":{"totalCount":7}},"tags":["minimalist","simple","clean","blog","responsive"]},{"repository":{"name":"showcase-hugo-theme","url":"https://github.com/apvarun/showcase-hugo-theme","updatedAt":"2020-07-20T14:41:37Z","forks":{"totalCount":4},"stargazers":{"totalCount":6}},"tags":["clean","gallery","minimal","minimalist","mobile","one page","personal","responsive","simple","single page","tailwind","starter","projects","white"]},{"repository":{"name":"hugo-html5up-alpha","url":"https://github.com/dewittn/hugo-html5up-alpha","updatedAt":"2020-07-25T17:04:28Z","forks":{"totalCount":4},"stargazers":{"totalCount":6}},"tags":["blog","html5up","responsive","business"]},{"repository":{"name":"hugo-theme-prav","url":"https://github.com/pravin/hugo-theme-prav","updatedAt":"2020-07-23T07:00:43Z","forks":{"totalCount":2},"stargazers":{"totalCount":6}},"tags":["website","responsive","disqus","blog","two-column"]},{"repository":{"name":"kiss-em","url":"https://github.com/pavel-pi/kiss-em","updatedAt":"2020-07-19T20:24:32Z","forks":{"totalCount":6},"stargazers":{"totalCount":6}},"tags":["blog","minimal","minimalist","responsive","rss"]},{"repository":{"name":"colordrop","url":"https://github.com/humrochagf/colordrop","updatedAt":"2020-07-30T18:43:20Z","forks":{"totalCount":2},"stargazers":{"totalCount":5}},"tags":["blog","customizable","monochromatic","mimimalist"]},{"repository":{"name":"hugo-theme-cactus","url":"https://github.com/monkeyWzr/hugo-theme-cactus","updatedAt":"2020-08-01T19:20:20Z","forks":{"totalCount":2},"stargazers":{"totalCount":5}},"tags":["blog","responsive","clean"]},{"repository":{"name":"osprey-delight","url":"https://github.com/kdevo/osprey-delight","updatedAt":"2020-07-26T19:08:51Z","forks":{"totalCount":2},"stargazers":{"totalCount":5}},"tags":["portfolio","gallery","minimalist","responsive","flexbox","fast","projects","onepage","fast"]},{"repository":{"name":"hugo-theme-sk1","url":"https://github.com/J-Siu/hugo-theme-sk1","updatedAt":"2020-07-31T23:39:07Z","forks":{"totalCount":0},"stargazers":{"totalCount":5}},"tags":["blog","clean","minimal","personal","simple"]},{"repository":{"name":"origin-hugo-theme","url":"https://github.com/fourtyone11/origin-hugo-theme","updatedAt":"2020-06-27T20:16:42Z","forks":{"totalCount":3},"stargazers":{"totalCount":5}},"tags":["blog","responsive","light","simple"]},{"repository":{"name":"hugo-tikva","url":"https://github.com/geschke/hugo-tikva","updatedAt":"2020-06-23T10:25:50Z","forks":{"totalCount":6},"stargazers":{"totalCount":5}},"tags":["theme","core","modern","responsive","bootstrap","minimal","blog","font awesome","white","dark","light"]},{"repository":{"name":"hugo-theme-techlog-simple","url":"https://github.com/mazgi/hugo-theme-techlog-simple","updatedAt":"2020-03-13T14:41:05Z","forks":{"totalCount":3},"stargazers":{"totalCount":5}},"tags":[]},{"repository":{"name":"classless-hugo","url":"https://github.com/fiatjaf/classless-hugo","updatedAt":"2019-07-08T18:21:55Z","forks":{"totalCount":0},"stargazers":{"totalCount":5}},"tags":["blog","personal"]},{"repository":{"name":"hugo-developer-portfolio","url":"https://github.com/samrobbins85/hugo-developer-portfolio","updatedAt":"2020-08-01T18:37:14Z","forks":{"totalCount":3},"stargazers":{"totalCount":4}},"tags":["portfolio","developer","responsive","uikit"]},{"repository":{"name":"ghazal","url":"https://github.com/darshanbaral/ghazal","updatedAt":"2020-06-19T02:44:07Z","forks":{"totalCount":3},"stargazers":{"totalCount":4}},"tags":["blog","personal"]},{"repository":{"name":"autophugo","url":"https://github.com/kc0bfv/autophugo","updatedAt":"2020-05-20T12:41:08Z","forks":{"totalCount":8},"stargazers":{"totalCount":4}},"tags":["gallery","photoblog","responsive","mobile","dark","creative","images"]},{"repository":{"name":"light-hugo","url":"https://github.com/tblyler/light-hugo","updatedAt":"2019-08-26T01:33:35Z","forks":{"totalCount":6},"stargazers":{"totalCount":4}},"tags":["responsive","nojs","minimal","normalize","light","white"]},{"repository":{"name":"hugo-h5bp-simple","url":"https://github.com/garvincasimir/hugo-h5bp-simple","updatedAt":"2019-08-17T23:16:14Z","forks":{"totalCount":1},"stargazers":{"totalCount":4}},"tags":["html5","responsive","simple","articles"]},{"repository":{"name":"hugo-theme-robotico","url":"https://github.com/wileybaba/hugo-theme-robotico","updatedAt":"2020-04-26T00:27:31Z","forks":{"totalCount":0},"stargazers":{"totalCount":4}},"tags":["fast","responsive","bootstrap","personal"]},{"repository":{"name":"hugo-eureka","url":"https://github.com/wangchucheng/hugo-eureka","updatedAt":"2020-07-22T13:57:41Z","forks":{"totalCount":4},"stargazers":{"totalCount":3}},"tags":["blog","responsive","simple","google analytics","multilingual","modern"]},{"repository":{"name":"hugo-theme-simple-blog","url":"https://github.com/10mohi6/hugo-theme-simple-blog","updatedAt":"2020-07-15T01:56:39Z","forks":{"totalCount":3},"stargazers":{"totalCount":3}},"tags":["simple","blog","responsive","minimal","clean","light","personal","bootstrap","customizable","hugo","theme"]},{"repository":{"name":"khata","url":"https://github.com/darshanbaral/khata","updatedAt":"2020-06-07T12:38:32Z","forks":{"totalCount":0},"stargazers":{"totalCount":3}},"tags":["documentation","simple"]},{"repository":{"name":"bodhi","url":"https://github.com/rhnvrm/bodhi","updatedAt":"2020-06-17T20:42:44Z","forks":{"totalCount":1},"stargazers":{"totalCount":3}},"tags":["blog","minimal","simple","personal","google-analytics","minimalist","search"]},{"repository":{"name":"hugo-assembly","url":"https://github.com/salsysd/hugo-assembly","updatedAt":"2020-02-21T02:29:52Z","forks":{"totalCount":9},"stargazers":{"totalCount":3}},"tags":["modern","company","simple","clean"]},{"repository":{"name":"bento","url":"https://github.com/leonardofaria/bento","updatedAt":"2020-07-31T05:14:29Z","forks":{"totalCount":0},"stargazers":{"totalCount":2}},"tags":["hugo","tailwindcss","minimal","minimalist","clean","simple","personal","google analytics","disqus","mobile","fast","syntax highlighting","white","modern"]},{"repository":{"name":"persian-hugo","url":"https://github.com/themefisher/persian-hugo","updatedAt":"2020-07-30T09:25:11Z","forks":{"totalCount":14},"stargazers":{"totalCount":2}},"tags":["landing-page","fast","light","white","modern","themefisher","hugo-theme","hugo-templates","bootstrap","blog","responsive","clean","simple","creative","contact-form","custom-themes","mobile","minimalistic","pages","resume","portfolio","google analytics","customizable","flexbox","presentation","product","theme","typography"]},{"repository":{"name":"basicwebtheme","url":"https://github.com/mdashx/basicwebtheme","updatedAt":"2020-07-18T11:40:24Z","forks":{"totalCount":0},"stargazers":{"totalCount":2}},"tags":["minimal","responsive","white","simple","clean","light","blog","readable"]},{"repository":{"name":"hugo-theme-notrack","url":"https://github.com/gevhaz/hugo-theme-notrack","updatedAt":"2020-07-29T22:11:24Z","forks":{"totalCount":2},"stargazers":{"totalCount":2}},"tags":["minimal","personal","responsive","libre","flexbox"]},{"repository":{"name":"hugo-fresh","url":"https://github.com/lucperkins/hugo-fresh","updatedAt":"2020-06-12T07:13:47Z","forks":{"totalCount":6},"stargazers":{"totalCount":2}},"tags":["responsive","one page","light","onepage","company","clean","landing page"]},{"repository":{"name":"hugo-scroll","url":"https://github.com/janraasch/hugo-scroll","updatedAt":"2020-08-01T13:49:55Z","forks":{"totalCount":0},"stargazers":{"totalCount":1}},"tags":["clean","contact","fontawesome","landing page","onepage","one page","personal","projects","simple","single page","starter","responsive","theme"]},{"repository":{"name":"hugo-theme-sk3","url":"https://github.com/J-Siu/hugo-theme-sk3","updatedAt":"2020-07-31T08:27:03Z","forks":{"totalCount":0},"stargazers":{"totalCount":1}},"tags":["blog","clean","customizable","dark","disqus","google adsense","google analytics","minimal","mobile","personal","responsive","simple"]},{"repository":{"name":"hugo-theme-pico","url":"https://github.com/negrel/hugo-theme-pico","updatedAt":"2020-08-01T16:44:29Z","forks":{"totalCount":1},"stargazers":{"totalCount":1}},"tags":["blog","light","multilingual","personal","resume","syntax highlightning","white"]},{"repository":{"name":"redgood","url":"https://github.com/urjaacharya/redgood","updatedAt":"2020-07-24T18:54:16Z","forks":{"totalCount":0},"stargazers":{"totalCount":1}},"tags":["personal","blog"]},{"repository":{"name":"hugo.386","url":"https://github.com/maxlefou/hugo.386","updatedAt":"2020-07-27T09:29:14Z","forks":{"totalCount":1},"stargazers":{"totalCount":1}},"tags":["blog","retro","geek","bootstra.386","hugo.386"]},{"repository":{"name":"the-roots-home","url":"https://github.com/rmsubekti/the-roots-home","updatedAt":"2020-07-22T11:15:24Z","forks":{"totalCount":1},"stargazers":{"totalCount":1}},"tags":["light","simple","folder","content"]},{"repository":{"name":"hugo-theme-sk2","url":"https://github.com/J-Siu/hugo-theme-sk2","updatedAt":"2020-07-29T09:30:45Z","forks":{"totalCount":0},"stargazers":{"totalCount":1}},"tags":["blog","clean","minimal","personal","simple"]},{"repository":{"name":"ticky_tacky_dark","url":"https://github.com/kc0bfv/ticky_tacky_dark","updatedAt":"2020-04-26T19:51:38Z","forks":{"totalCount":4},"stargazers":{"totalCount":1}},"tags":["responsive","bootstrap","personal","blog","mobile","dark","creative","images","multipage","accessible"]},{"repository":{"name":"papaya","url":"https://github.com/plopcas/papaya","updatedAt":"2020-07-12T12:51:16Z","forks":{"totalCount":1},"stargazers":{"totalCount":1}},"tags":["blog"]},{"repository":{"name":"hugo-theme-sky","url":"https://github.com/cfrome77/hugo-theme-sky","updatedAt":"2019-10-28T18:48:03Z","forks":{"totalCount":3},"stargazers":{"totalCount":1}},"tags":["simple","minimal","blog","disqus"]},{"repository":{"name":"hugo-minimalist-spa","url":"https://github.com/Sag-Dev/hugo-minimalist-spa","updatedAt":"2019-09-30T16:34:35Z","forks":{"totalCount":2},"stargazers":{"totalCount":1}},"tags":["minimalist","spa","singlepage","business","professional","simple"]},{"repository":{"name":"health-science-journal","url":"https://github.com/epistemehealth/health-science-journal","updatedAt":"2020-07-29T15:28:44Z","forks":{"totalCount":0},"stargazers":{"totalCount":0}},"tags":["journal","health sciences"]},{"repository":{"name":"hugo-theme-color-your-world","url":"https://github.com/rmaguiar/hugo-theme-color-your-world","updatedAt":"2020-07-29T13:47:57Z","forks":{"totalCount":0},"stargazers":{"totalCount":0}},"tags":["accessible","blog","contact form","dark","fast","highlighting","light","minimalist","modern","multilingual","personal","responsive","search","technical"]},{"repository":{"name":"hugo-story","url":"https://github.com/caressofsteel/hugo-story","updatedAt":"2020-07-24T21:56:28Z","forks":{"totalCount":0},"stargazers":{"totalCount":0}},"tags":["blog","clean","html5up","modular","one-page","portfolio","responsive"]},{"repository":{"name":"flexible-seo-hugo","url":"https://github.com/pjbakker/flexible-seo-hugo","updatedAt":"2020-06-09T14:58:47Z","forks":{"totalCount":0},"stargazers":{"totalCount":0}},"tags":["bootstrap","customizable","responsive"]},{"repository":{"name":"ronu-hugo-theme","url":"https://github.com/softwareyoga/ronu-hugo-theme","updatedAt":"2020-06-12T21:04:00Z","forks":{"totalCount":1},"stargazers":{"totalCount":0}},"tags":["blog","responsive","minimal","clean","simple","google-analytics","minimalist","syntax-highlighting","minimalistic"]},{"repository":{"name":"someparts-hugo","url":"https://github.com/tastaturtier/someparts-hugo","updatedAt":"2020-02-18T02:44:39Z","forks":{"totalCount":0},"stargazers":{"totalCount":0}},"tags":["responsive","bootstrap","fontawesome","minimalist","simple","google analytics","projects","product"]},{"repository":{"name":"hugo-theme-cole","url":"https://github.com/jacobsun/hugo-theme-cole","updatedAt":"2019-11-03T17:27:20Z","forks":{"totalCount":0},"stargazers":{"totalCount":0}},"tags":["minimal","light","simple"]}]